django_storage_webdav/__init__.py
django_storage_webdav/storage.py
django_storage_webdav-0.1.2.dist-info/LICENSE.txt
django_storage_webdav-0.1.2.dist-info/METADATA
django_storage_webdav-0.1.2.dist-info/WHEEL
django_storage_webdav-0.1.2.dist-info/top_level.txt
django_storage_webdav-0.1.2.dist-info/RECORD
