Metadata-Version: 2.1
Name: django-storage-webdav
Version: 0.1.2
Summary: Django Storage System for WebDAV
Home-page: https://gitlab.com/apalsson/django-webdav-storage
Author: A. Palsson
Author-email: contact@apalsson.info
License: UNKNOWN
Platform: UNKNOWN
Classifier: Development Status :: 4 - Beta
Classifier: Framework :: Django :: 2.2
Classifier: Intended Audience :: Developers
Classifier: License :: OSI Approved :: BSD License
Classifier: Operating System :: OS Independent
Classifier: Programming Language :: Python :: 3
Requires-Python: >=3.5
Requires-Dist: django (>=2.2)
Requires-Dist: lxml
Requires-Dist: python-dateutil
Requires-Dist: requests
